main.py
setup.py
MTVQA.egg-info/PKG-INFO
MTVQA.egg-info/SOURCES.txt
MTVQA.egg-info/dependency_links.txt
MTVQA.egg-info/requires.txt
MTVQA.egg-info/top_level.txt